streamlit_markdown/__init__.py
streamlit_markdown/frontend/out/404.html
streamlit_markdown/frontend/out/_next/static/L1CT3xOnruN-6J2UbtRzt/_buildManifest.js
streamlit_markdown/frontend/out/_next/static/L1CT3xOnruN-6J2UbtRzt/_ssgManifest.js
streamlit_markdown/frontend/out/_next/static/chunks/128.4d9231bbd09e3c13.js
streamlit_markdown/frontend/out/_next/static/chunks/129.9efdded3503e2056.js
streamlit_markdown/frontend/out/_next/static/chunks/15.767906eca7c842ec.js
streamlit_markdown/frontend/out/_next/static/chunks/162.9993134950e5aae2.js
streamlit_markdown/frontend/out/_next/static/chunks/172.4568e3e47a7b0d6c.js
streamlit_markdown/frontend/out/_next/static/chunks/175675d1-5839900ee54d9685.js
streamlit_markdown/frontend/out/_next/static/chunks/289.c3641639ea07261c.js
streamlit_markdown/frontend/out/_next/static/chunks/327.3ff3126ba5f69a76.js
streamlit_markdown/frontend/out/_next/static/chunks/336.c3ee2e7484c89406.js
streamlit_markdown/frontend/out/_next/static/chunks/3a3990a6-7141d383e7e655e4.js
streamlit_markdown/frontend/out/_next/static/chunks/407.1f033106645f6827.js
streamlit_markdown/frontend/out/_next/static/chunks/449.368de69e44e91daf.js
streamlit_markdown/frontend/out/_next/static/chunks/474.c95c7a055f8a822b.js
streamlit_markdown/frontend/out/_next/static/chunks/493.8a17d5547315436c.js
streamlit_markdown/frontend/out/_next/static/chunks/518.a072e9351f53ceee.js
streamlit_markdown/frontend/out/_next/static/chunks/553.8317b30d3e990326.js
streamlit_markdown/frontend/out/_next/static/chunks/57.5c87ccbc7fc65323.js
streamlit_markdown/frontend/out/_next/static/chunks/585.718c889433935045.js
streamlit_markdown/frontend/out/_next/static/chunks/616.62b94ea455be6fb0.js
streamlit_markdown/frontend/out/_next/static/chunks/644.b993fb3718a827b7.js
streamlit_markdown/frontend/out/_next/static/chunks/650.a33183e56716c341.js
streamlit_markdown/frontend/out/_next/static/chunks/705.af52d38cf2fd4da4.js
streamlit_markdown-1.0.9.dist-info/LICENSE
streamlit_markdown-1.0.9.dist-info/METADATA
streamlit_markdown-1.0.9.dist-info/WHEEL
streamlit_markdown-1.0.9.dist-info/RECORD
