Metadata-Version: 2.1
Name: streamlit-markdown
Version: 1.0.9
Summary: A Streamlit component to display markdown, which supports table, code switch, LaTeX, mermaid, and more.
Home-page: https://github.com/LinXueyuanStdio/streamlit-markdown
License: MIT
Author: Xueyuan Lin
Author-email: linxy59@mail2.sysu.eud.cn
Requires-Python: >=3.8, !=2.7.*, !=3.0.*, !=3.1.*, !=3.2.*, !=3.3.*, !=3.4.*, !=3.5.*, !=3.6.*, !=3.7.*
Classifier: License :: OSI Approved :: MIT License
Classifier: Programming Language :: Python :: 3
Classifier: Programming Language :: Python :: 3.8
Classifier: Programming Language :: Python :: 3.9
Classifier: Programming Language :: Python :: 3.10
Classifier: Programming Language :: Python :: 3.11
Classifier: Programming Language :: Python :: 3.12
Requires-Dist: streamlit (>=0.63)
